AUTHORS.rst
CHANGELOG.rst
CONTRIBUTING.rst
LICENSE
MANIFEST.in
README.rst
setup.cfg
setup.py
tox.ini
ci/bootstrap.py
ci/requirements.txt
ci/templates/.github/workflows/github-actions.yml
docs/authors.rst
docs/changelog.rst
docs/conf.py
docs/contributing.rst
docs/index.rst
docs/installation.rst
docs/readme.rst
docs/requirements.txt
docs/spelling_wordlist.txt
docs/usage.rst
docs/reference/Audio_proc_lib.rst
docs/reference/index.rst
src/Audio_proc_lib/__init__.py
src/Audio_proc_lib/__main__.py
src/Audio_proc_lib/audio_proc_functions.py
src/Audio_proc_lib/cli.py
src/Audio_proc_lib.egg-info/PKG-INFO
src/Audio_proc_lib.egg-info/SOURCES.txt
src/Audio_proc_lib.egg-info/dependency_links.txt
src/Audio_proc_lib.egg-info/not-zip-safe
src/Audio_proc_lib.egg-info/requires.txt
src/Audio_proc_lib.egg-info/top_level.txt
tests/test_Audio_proc_lib.py