Metadata-Version: 2.1
Name: Audio-proc-lib
Version: 0.0.1
Summary: A library that contains basic audio signal processing functionalities
Home-page: https://github.com/nnanos/Audio_proc_lib
Author: Nanos Nikolaos
Author-email: nnanos@ceid.upatras.gr
License: MIT
Project-URL: Documentation, https://Audio_proc_lib.readthedocs.io/
Project-URL: Changelog, https://Audio_proc_lib.readthedocs.io/en/latest/changelog.html
Project-URL: Issue Tracker, https://github.com/nnanos/Audio_proc_lib/issues
Platform: UNKNOWN
Classifier: Development Status :: 5 - Production/Stable
Classifier: Intended Audience :: Developers
Classifier: License :: OSI Approved :: MIT License
Classifier: Operating System :: Unix
Classifier: Operating System :: POSIX
Classifier: Operating System :: Microsoft :: Windows
Classifier: Programming Language :: Python
Classifier: Programming Language :: Python :: 3
Classifier: Programming Language :: Python :: 3 :: Only
Classifier: Programming Language :: Python :: 3.6
Classifier: Programming Language :: Python :: 3.7
Classifier: Programming Language :: Python :: 3.8
Classifier: Programming Language :: Python :: 3.9
Classifier: Programming Language :: Python :: 3.10
Classifier: Programming Language :: Python :: Implementation :: CPython
Classifier: Programming Language :: Python :: Implementation :: PyPy
Classifier: Topic :: Utilities
Requires-Python: >=3.6
License-File: LICENSE
License-File: AUTHORS.rst
